setup.py
mlnd_probability/Binomialdistribution.py
mlnd_probability/Gaussiandistribution.py
mlnd_probability/Generaldistribution.py
mlnd_probability/__init__.py
mlnd_probability.egg-info/PKG-INFO
mlnd_probability.egg-info/SOURCES.txt
mlnd_probability.egg-info/dependency_links.txt
mlnd_probability.egg-info/not-zip-safe
mlnd_probability.egg-info/top_level.txt