Metadata-Version: 1.0
Name: mlnd-probability
Version: 0.1
Summary: Gaussian distributions
Home-page: UNKNOWN
Author: Ahmed Shoukr
Author-email: ahmedshoukr10@gmail.com
License: UNKNOWN
Platform: UNKNOWN
